{
    "0": "('spectator-consumer.euw1.lol.pvp.net:80', 'qbbmc9Ka4GTDtzstHSYVKnPnwSuGXpR1', '6448453497', 'EUW1')",
    "Background": "Custom.png",
    "Stats": {
        "T1": "Aatrox Akshan Lulu Rengar Lux",
        "T2": "Viego Taric Cassiopeia Sion LeBlanc"
    },
    "TG": [
        "\u2605 Stats on 7 | 5 matches \u2605\n\n",
        "\ud83d\udc2c\u041f1 Fiora - Darius - Talon - Veigar - Sylas -- 28.6% \ud83d\udd34\n",
        "\ud83d\udc19\u041f2 Pyke - Senna - Nidalee - Swain - Sivir -- 71.4% \ud83d\udd34\n\n",
        "\ud83d\udd3460.0%  --  \u0411 90.5 \u041c  --  40.0%\ud83d\udd34"
    ],
    "CheckerLast": "Inevitabl\u00ea:TR",
    "MatchesARAM": {
        "BR1": [
            "Nautilus | Caitlyn | Morgana | Kayle | MissFortune-|-The goddess Aqua:BR",
            "Sylas | Shaco | Taliyah | Rammus | Riven-|-Ki Sono :BR",
            "Xayah | Nautilus | Zoe | Talon | Maokai-|-Darknesdark:BR",
            "Lissandra | Milio | Zeri | Kennen | MasterYi-|-Nagai Michinori:BR",
            "Jax | Nilah | Sylas | Sona | Udyr-|-KDaher:BR"
        ],
        "EUN1": [
            "TwistedFate | Ekko | Sivir | Shaco | Draven-|-\u00c1j h\u00e9t disz g\u00e9m:EUNE",
            "Samira | Yone | Ivern | Gangplank | Rell-|-A1M:EUNE",
            "Varus | Syndra | Samira | Ezreal | Sylas-|-Tsourtsou:EUNE",
            "Zyra | Ezreal | Qiyana | Hecarim | RekSai-|-KatFromHell:EUNE",
            "Zilean | JarvanIV | Rell | Taliyah | Ahri-|-MINI CHAD:EUNE"
        ],
        "EUW1": [
            "MasterYi | Vayne | Zoe | Veigar | Leona-|-naoal:EUW",
            "Malzahar | Quinn | LeBlanc | Karma | Viktor-|-CannotHaveSex:EUW",
            "KaiSa | Aatrox | Sylas | Senna | Fiddlesticks-|-Kurald Thyrllan:EUW",
            "Blitzcrank | Lux | Gwen | Darius | LeBlanc-|-17 year old car:EUW",
            "Viego | Orianna | Nami | LeBlanc | Jinx-|-SpARRoWZZs:EUW"
        ],
        "JP1": [
            "Mordekaiser | Hecarim | Ezreal | Aatrox | Swain-|-AiUiOi:JP",
            "Ezreal | Jhin | TwistedFate | Shaco | Gnar-|-kona2:JP",
            "Jinx | Tryndamere | Ashe | KhaZix | Gangplank-|-Ricyzu:JP",
            "Thresh | KhaZix | Nilah | Maokai | Zoe-|-Air:JP",
            "LeeSin | Illaoi | Renata | KaiSa | Yasuo-|-MonkeyTurn:JP"
        ],
        "KR": [
            "LeeSin | Nasus | LeBlanc | Akshan | Yone-|-\uc544\uc624 \ud398\ub9ac\uc2dc\uce58 \ucacc:KR",
            "Neeko | Aphelios | Lulu | KSante | Lissandra-|-\uad00 \ubaa8:KR",
            "Fiora | Fizz | Lulu | BelVeth | Twitch-|-\ubabb\ud558\ub2c8\uc0b4\uc0b4:KR",
            "Swain | Gragas | Kennen | Nilah | KhaZix-|-stgusdt:KR",
            "KhaZix | AurelionSol | Hecarim | Yuumi | Aphelios-|-\uc8fd \ubcc0 \ud56d:KR"
        ],
        "LA1": [
            "Seraphine | Wukong | Irelia | AurelionSol | Rell-|-Chomp:LAN",
            "Rakan | Renekton | Katarina | Lillia | Akali-|-xSimon:LAN",
            "Leona | Senna | Warwick | Aphelios | Ryze-|-mauri8499:LAN",
            "KSante | Yuumi | Akshan | Zeri | Viego-|-D\u00e9nji:LAN",
            "Evelynn | Rengar | Kayn | Kassadin | Aatrox-|-Lunella:LAN"
        ],
        "LA2": [
            "Janna | Diana | Yorick | Mordekaiser | Bard-|-MarcoAureIion:LAS",
            "Pyke | Varus | Ahri | Annie | Milio-|-MainDepresion:LAS",
            "Darius | Lillia | TwistedFate | Zilean | Hecarim-|-TQY ElGatoRocoso:LAS",
            "Fizz | Malzahar | Warwick | Samira | Wukong-|-ThenAmIDaMonster:LAS",
            "Karma | Zoe | Blitzcrank | LeBlanc | Draven-|-\u00c2nzu:LAS"
        ],
        "NA1": [
            "Tristana | MissFortune | Neeko | Trundle | Janna-|-Birbatiel:NA",
            "Milio | Riven | Azir | Lucian | LeeSin-|-hamz:NA",
            "Akshan | Akali | Galio | ChoGath | Sett-|-Light777:NA",
            "Mordekaiser | Blitzcrank | Senna | Riven | Zed-|-Captain Skippy1:NA",
            "Aatrox | Renata | Gragas | Aphelios | Qiyana-|-FEAR KELTHUZAD:NA"
        ],
        "OC1": [
            "Thresh | Volibear | Brand | Evelynn | Riven-|-CaraHearst:OCE",
            "Twitch | Graves | Irelia | Ahri | Yasuo-|-Flj\u00f3tav\u00edk:OCE",
            "JarvanIV | Malphite | Zed | Samira | Zac-|-\u00dfread pitt:OCE",
            "Vayne | Brand | Varus | Viktor | Sett-|-LuvibleMaster:OCE",
            "Renekton | Lissandra | Malzahar | Darius | Tristana-|-d1p:OCE"
        ],
        "RU": [
            "Fizz | Malzahar | Braum | BelVeth | Kalista-|-ppppppppppjj:RU",
            "Sion | Lillia | KaiSa | Pyke | Gragas-|-LoNDJeRon:RU",
            "Nami | Viktor | Syndra | KhaZix | Nidalee-|-Alvoro:RU",
            "Xayah | Anivia | Zoe | Yorick | Maokai-|-N\u0430meless:RU",
            "Corki | Lulu | Swain | Warwick | Senna-|-\u0417\u043c\u0435\u0439:RU"
        ],
        "TR1": [
            "Lulu | Thresh | Kennen | Brand | Varus-|-chavelor:TR",
            "Aatrox | Akshan | Lulu | Rengar | Lux-|-Inevitabl\u00ea:TR",
            "Sett | Varus | Samira | Galio | Shaco-|-Ryuuj\u00een Jakka:TR",
            "Kennen | Mordekaiser | Vayne | Irelia | Janna-|-Saviour:TR",
            "Lux | TwistedFate | Anivia | Draven | Fiddlesticks-|-\u00eaugene:TR"
        ],
        "VN2": [
            "Cassiopeia | Karma | Gwen | Twitch | Ivern-|-Im Donny:VN",
            "Syndra | Swain | Varus | Ashe | Sylas-|-kl\u00efm:VN",
            "LeBlanc | Kayle | Ahri | Swain | RekSai-|-26022023:VN",
            "LeBlanc | Fiddlesticks | Graves | Neeko | Varus-|-V\u1ecbt Anh t\u1edbi:VN",
            "Amumu | Diana | Tristana | Fiddlesticks | Nidalee-|-T1 Ngumaconsi:VN"
        ],
        "SG2": [
            "Karma | Nautilus | Lux | Zed | Tristana-|-pooboytroll:SG",
            "Diana | Nasus | LeBlanc | Yone | Zed-|-Fami:SG",
            "KSante | Viktor | Sivir | Senna | Azir-|-Pootato:SG",
            "MasterYi | Draven | Aatrox | Corki | Viktor-|-100:SG",
            "Wukong | TahmKench | Ekko | Lucian | Xerath-|-\u00e8dgy:SG"
        ],
        "PH2": [
            "Twitch | Ahri | Nautilus | Zyra | Shyvana-|-Ford Raptor:PH",
            "Ezreal | Riven | Ornn | Aphelios | KhaZix-|-Xynical:PH",
            "Katarina | Ivern | Jax | Varus | Lulu-|-WVL8 Lilocuti:PH",
            "Bard | Zed | Jinx | Veigar | TahmKench-|-Dirk:PH",
            "Rammus | Morgana | Caitlyn | Viego | Fiddlesticks-|-Peek A Box:PH"
        ],
        "TH2": [
            "Ezreal | Thresh | Sion | Neeko | Kassadin-|-MASTER OF GODESS:TH",
            "Garen | Zilean | Aphelios | Wukong | KaiSa-|-WindnZI:TH",
            "Jayce | LeBlanc | Morgana | XinZhao | Lucian-|-\u0e0a\u0e32\u0e0d\u0e44\u0e0a\u0e22:TH",
            "Xerath | Jhin | Amumu | Poppy | Vladimir-|-Brunnhilde:TH",
            "Graves | Rakan | Fiora | Veigar | Ashe-|-Reluctant Player:TH"
        ],
        "TW2": [
            "Ashe | Xerath | Taliyah | Akshan | Vladimir-|-\u860b\u679c\u725b\u59761:TW",
            "Ezreal | Qiyana | Lux | Wukong | Vladimir-|-Ezz:TW",
            "Galio | Sylas | Katarina | Vladimir | Draven-|-DeatGiggle:TW",
            "Aphelios | Ornn | Shen | Alistar | Lissandra-|-\u7d14\u89dc\u7cb9:TW",
            "Shaco | Ekko | Gnar | Milio | Tristana-|-\u6211\u63a8\u7684\u863f\u8389:TW"
        ]
    },
    "MatchesRift": [
        "Akali | LeBlanc | TwistedFate | Zilean | Jayce-|-ynzaapez:TW:UN",
        "Tristana | Ahri | Zilean | Annie | Darius-|-Raloxifene:NA:UN",
        "Sett | KaiSa | Cassiopeia | Zilean | Taric-|-DiWooooo:NA:UN",
        "Amumu | Lulu | KogMaw | Zilean | Elise-|-SKT Cloner:NA:SI",
        "Rengar | Thresh | Tristana | Jax | Yasuo-|-ThickSquidee:NA:SI",
        "Vayne | Zilean | Gragas | Thresh | Talon-|-Mugetshu:TR:BR",
        "Jax | Xayah | Zilean | Lillia | Yone-|-Eunseok:EUW:PL",
        "Vayne | Malphite | MasterYi | Brand | Fizz-|-Elmaga15:LAN:SI",
        "Ezreal | Skarner | Zilean | Neeko | Teemo-|-Jaded Life:NA:PL",
        "ChoGath | Viego | Milio | Nilah | Yone-|-alexchu999:LAS:GO",
        "Shaco | Akali | Malphite | Samira | Yuumi-|-Ugoman:NA:UN",
        "Draven | Zoe | LeBlanc | Zilean | Gragas-|-BamDal:NA:UN",
        "Viktor | Jhin | Jinx | MasterYi | Galio-|-Dekade:BR:GO",
        "Samira | Milio | Veigar | Zilean | Thresh-|-RedMoon97:LAN:UN",
        "Zilean | Teemo | Poppy | Aphelios | Veigar-|-6uo bbg iloveu:EUW:GO",
        "Xayah | Sett | KaiSa | Nidalee | Nunu-|-SkyPanda:BR:GO",
        "Bard | Ryze | Annie | Sion | Sejuani-|-Llyriad:NA:UN",
        "Shyvana | KSante | Akali | Jinx | Senna-|-i poo on kids:NA:GO",
        "Ekko | Malzahar | Blitzcrank | Nocturne | Sett-|-Sniper King XD:NA:SI",
        "Sivir | ChoGath | TahmKench | Nidalee | Ziggs-|-PhilCollinsRadio:NA:PL",
        "Ornn | Nasus | Seraphine | Evelynn | Ezreal-|-RiceKrispyTreat:NA:UN",
        "Caitlyn | Zilean | Blitzcrank | Maokai | KaiSa-|-LamaPocosxx:OCE:UN",
        "Zilean | Sivir | Ziggs | Lissandra | JarvanIV-|-Pugilicious:OCE:UN",
        "Lux | Ashe | Caitlyn | Alistar | Tryndamere-|-zuuzu:NA:SI",
        "Ashe | Mordekaiser | Cassiopeia | MissFortune | Senna-|-DieselSak:NA:BR",
        "Yone | Rammus | Katarina | Sivir | Akali-|-ITIint:NA:UN",
        "TwistedFate | Draven | Ahri | Pantheon | Malzahar-|-Ardure:NA:UN",
        "Veigar | Tristana | Milio | Corki | Morgana-|-ThislsMyAccount:EUNE:SI"
    ]
}